[
    {
        "ts": "1546885490.003800",
        "text": "<@UF8B49RC2> has joined the channel",
        "user": "UF8B49RC2",
        "type": "message"
    },
    {
        "ts": "1546916871.004300",
        "text": "<@UFA3RBEUE> has joined the channel",
        "user": "UFA3RBEUE",
        "type": "message"
    },
    {
        "ts": "1546942393.004600",
        "text": "<@UF84P23L0> has joined the channel",
        "user": "UF84P23L0",
        "type": "message"
    },
    {
        "ts": "1546992643.004900",
        "text": "<@UF8SE896V> has joined the channel",
        "user": "UF8SE896V",
        "type": "message"
    },
    {
        "ts": "1547013174.005400",
        "text": "<@UF9JH176E> has joined the channel",
        "user": "UF9JH176E",
        "type": "message"
    },
    {
        "ts": "1547022065.005600",
        "text": "昔の話ですが,職場のOSがWin10になり,新しいGHCが使えるようになったのでAttoparsec.Text.Lazyで実装したら3分の1ほどのメモリ消費になりました.",
        "user": "UEC0PN1PA",
        "type": "message"
    },
    {
        "ts": "1547087383.006700",
        "text": "<@UFAJVD0VB> has joined the channel",
        "user": "UFAJVD0VB",
        "type": "message"
    },
    {
        "ts": "1547119093.007000",
        "text": "<@UFBM9CL23> has joined the channel",
        "user": "UFBM9CL23",
        "type": "message"
    },
    {
        "ts": "1547427607.007200",
        "text": "Reminder: <https://haskell-jp.slack.com/archives/C4LFB6DE0/p1517792426000233>",
        "user": "USLACKBOT",
        "type": "message"
    },
    {
        "ts": "1547525697.007500",
        "text": "<@UFDJAUMSP> has joined the channel",
        "user": "UFDJAUMSP",
        "type": "message"
    },
    {
        "ts": "1547535496.007900",
        "text": "<@UFDKZJBLK> has joined the channel",
        "user": "UFDKZJBLK",
        "type": "message"
    },
    {
        "ts": "1547631818.008200",
        "text": "<@UFE5C32DN> has joined the channel",
        "user": "UFE5C32DN",
        "type": "message"
    },
    {
        "ts": "1547644276.008400",
        "text": "<@UFES5NULC> has joined the channel",
        "user": "UFES5NULC",
        "type": "message"
    },
    {
        "ts": "1547703542.008500",
        "text": "質問させていただきます. TemplateHaskell で以下のコードでコンパイル時に文字列を埋め込んでいます. UTF-8のcsvファイルの数値等は問題なく読み込めるのですが,日本語を埋め込む際に何故か先頭に｢・｣(中点)が入り込み困っています. この現象の原因に心当たりがありましたらご教示下さい. 環境は Win10 Docker for Windows 上のCent OS 7, GHC 8.6.3 です.",
        "user": "UEC0PN1PA",
        "type": "message"
    },
    {
        "ts": "1547704890.009100",
        "text": "本題じゃないですが、\n```\n\tlift t + [|TL.pack $(lift $TL.unpack t) |]\n```\nの `+` は `=` のまちがいですかね？",
        "user": "U4L0B71L1",
        "type": "message"
    },
    {
        "ts": "1547705021.009300",
        "text": "はい,間違いです. ご指摘ありがとうございます.",
        "user": "UEC0PN1PA",
        "type": "message"
    },
    {
        "ts": "1547705053.009600",
        "text": "修正させていただきました.",
        "user": "UEC0PN1PA",
        "type": "message"
    },
    {
        "ts": "1547706305.009900",
        "text": "大変申し訳ありませんが,自己解決しました.\nエディタの関係でBOMの\\65279が記述されており,TemplateHaskellがそれを書き込んでいたようです.",
        "user": "UEC0PN1PA",
        "type": "message"
    },
    {
        "ts": "1547737304.010700",
        "text": "<@UFG7U49H8> has joined the channel",
        "user": "UFG7U49H8",
        "type": "message"
    },
    {
        "ts": "1548032422.011400",
        "text": "Reminder: <https://haskell-jp.slack.com/archives/C4LFB6DE0/p1517792426000233>",
        "user": "USLACKBOT",
        "type": "message"
    },
    {
        "ts": "1548310870.011700",
        "text": "<@UFMV026NR> has joined the channel",
        "user": "UFMV026NR",
        "type": "message"
    },
    {
        "ts": "1548371654.012200",
        "text": "<@UFNL9EP98> has joined the channel",
        "user": "UFNL9EP98",
        "type": "message"
    },
    {
        "ts": "1548383488.012500",
        "text": "<@UFPRHDT8X> has joined the channel",
        "user": "UFPRHDT8X",
        "type": "message"
    },
    {
        "ts": "1548433844.012800",
        "text": "<@UFP7VJHGT> has joined the channel",
        "user": "UFP7VJHGT",
        "type": "message"
    },
    {
        "ts": "1548478679.013100",
        "text": "<@UFQTA7495> has joined the channel",
        "user": "UFQTA7495",
        "type": "message"
    },
    {
        "ts": "1548479046.013400",
        "text": "<@UFQ22CCCD> has joined the channel",
        "user": "UFQ22CCCD",
        "type": "message"
    },
    {
        "ts": "1548482409.013700",
        "text": "<@UFP82PUF3> has joined the channel",
        "user": "UFP82PUF3",
        "type": "message"
    },
    {
        "ts": "1548637221.013900",
        "text": "Reminder: <https://haskell-jp.slack.com/archives/C4LFB6DE0/p1517792426000233>",
        "user": "USLACKBOT",
        "type": "message"
    },
    {
        "ts": "1548664670.014200",
        "text": "<@UFPSK1JNL> has joined the channel",
        "user": "UFPSK1JNL",
        "type": "message"
    },
    {
        "ts": "1548745351.014500",
        "text": "<@UFR40Q0U9> has joined the channel",
        "user": "UFR40Q0U9",
        "type": "message"
    },
    {
        "ts": "1548910075.014900",
        "text": "<@UFTURES03> has joined the channel",
        "user": "UFTURES03",
        "type": "message"
    },
    {
        "ts": "1549002044.015300",
        "text": "<@UFUMHSDPB> has joined the channel",
        "user": "UFUMHSDPB",
        "type": "message"
    },
    {
        "ts": "1549242009.015800",
        "text": "Reminder: <https://haskell-jp.slack.com/archives/C4LFB6DE0/p1517792426000233>",
        "user": "USLACKBOT",
        "type": "message"
    },
    {
        "ts": "1549333866.017100",
        "text": "<@UFY4AK342> has joined the channel",
        "user": "UFY4AK342",
        "type": "message"
    },
    {
        "ts": "1549401729.017400",
        "text": "<@UFYU7K1DH> has joined the channel",
        "user": "UFYU7K1DH",
        "type": "message"
    },
    {
        "ts": "1549421822.017800",
        "text": "<@UFZ5LD0H1> has joined the channel",
        "user": "UFZ5LD0H1",
        "type": "message"
    },
    {
        "ts": "1549447383.018100",
        "text": "<@UFZLMTQQ5> has joined the channel",
        "user": "UFZLMTQQ5",
        "type": "message"
    },
    {
        "ts": "1549556705.018400",
        "text": "<@UG0QR8Y7N> has joined the channel",
        "user": "UG0QR8Y7N",
        "type": "message"
    },
    {
        "ts": "1549629516.018700",
        "text": "<@UG1NKET4K> has joined the channel",
        "user": "UG1NKET4K",
        "type": "message"
    }
]