{
  "workspaceName": "haskell-jp",
  "timeZone": "Asia/Tokyo",
  "targetChannels": {
    "CL3AXB1AL": "Public  # atcoder-lang-update",
    "CR2TETE5R": "Public  # beginners",
    "C8KBGEBR7": "Public  # code-review",
    "C4P499EPQ": "Public  # english",
    "CR4U9PBLL": "Public  # english-help",
    "C4LFB6DE0": "Public  # general",
    "CAXQ09PN2": "Public  # haskell-day",
    "C7Y71415W": "Public  # math",
    "C5666B6BB": "Public  # questions",
    "C4M4TT8JJ": "Public  # random",
    "C8R0H137H": "Public  # translation",
    "CCYF8H43A": "Public  # nix",
    "CD87P78HF": "Public  # mmlh",
    "CE368SB5G": "Public  # ghc8x",
    "CGT2Q4KHP": "Public  # hatchobori-haskell",
    "CM4J6EDHR": "Public  # icfp",
    "CN3P057K8": "Public  # haskell-day-sponsor",
    "GDTFWM8KX": "Private # haskell-day-staff"
  }
}
