[
    {
        "ts": "1597486079.058500",
        "text": "これが早く来てくれると嬉しいんですけどねｗ\n<https://nework.app/about/>",
        "user": "U4KPPQW7K",
        "type": "message"
    },
    {
        "ts": "1597486128.058900",
        "text": "名前大丈夫？WeWorkに怒られない？ :sweat_smile:",
        "user": "U4LGTMTMK",
        "type": "message"
    },
    {
        "ts": "1597486139.059100",
        "text": "ホントだｗｗｗｗ",
        "user": "U4KPPQW7K",
        "type": "message"
    },
    {
        "ts": "1597486212.059300",
        "text": "NTTComともあろう会社が... SoftBankにけんか売ってるとしか思えない。（まだSoftBankがWeWorkもってたかは忘れたけど）",
        "user": "U4LGTMTMK",
        "type": "message"
    },
    {
        "ts": "1597486228.059500",
        "text": "持ってますよｗ",
        "user": "U4KPPQW7K",
        "type": "message"
    },
    {
        "ts": "1597487061.059900",
        "text": "ようやく原因がわかって直せました... :tired_face:\n<https://twitter.com/igrep/status/1294580249129172993>",
        "user": "U4LGTMTMK",
        "type": "message"
    },
    {
        "ts": "1597505748.060500",
        "text": "どちらもOKです！",
        "user": "U59TQ3MJ9",
        "type": "message"
    },
    {
        "ts": "1597543750.060800",
        "text": "<@U4L0B71L1> 約一月ぶりと言うことで次回はお願いします！ :pray:",
        "user": "U4LGTMTMK",
        "type": "message"
    },
    {
        "ts": "1597544239.062400",
        "text": "独り言: 朝日ネットさんさえよければそろそろリアル会場でもやりたいなぁ。懇親会さえやらなければ十分リスクは下げられると思うのですよね。万が一クラスターが出てしまった場合に朝日ネットが被る迷惑を考えると悩ましいですが :disappointed_relieved:",
        "user": "U4LGTMTMK",
        "type": "message"
    },
    {
        "ts": "1597562672.062600",
        "text": "<@U4LGTMTMK> 合点承知",
        "user": "U4L0B71L1",
        "type": "message"
    },
    {
        "ts": "1597564150.062900",
        "text": " set up a reminder “「第46回 Haskell-jp もくもく会」のお時間です！\n自己紹介と今日やりたいことを書き込みましょう” in this channel at 1PM Sunday, August 23rd, Japan Standard Time.",
        "user": "U4L0B71L1",
        "type": "message"
    },
    {
        "ts": "1597564605.063100",
        "text": " set up a reminder “成果報告のお時間です！\nしたことを共有しましょう” in this channel at 6PM Sunday, August 23rd, Japan Standard Time.",
        "user": "U4L0B71L1",
        "type": "message"
    },
    {
        "ts": "1598155209.000100",
        "text": "Reminder: 「第46回 Haskell-jp もくもく会」のお時間です！\n自己紹介と今日やりたいことを書き込みましょう",
        "user": "USLACKBOT",
        "type": "message"
    },
    {
        "ts": "1598155216.000300",
        "text": "さてさて",
        "user": "U4L0B71L1",
        "type": "message"
    },
    {
        "ts": "1598155291.000700",
        "text": "Haskell インタープリター作っていきます",
        "user": "U4L0B71L1",
        "type": "message"
    },
    {
        "ts": "1598155485.001900",
        "text": "山本悠滋です。\n<https://mokudev-tokyo.connpass.com/event/186204/|https://mokudev-tokyo.connpass.com/event/186204/> の会場から同時に参加します。\nいつも通りSlack APIの件の続きです",
        "user": "U4LGTMTMK",
        "type": "message"
    },
    {
        "ts": "1598157580.002800",
        "text": "Algorithm Design with Haskell - Ch 1. Exercises",
        "user": "U584T7GAH",
        "type": "message"
    },
    {
        "ts": "1598160451.003300",
        "text": "久しぶりに参加します. gksatoです。昨日のABC 176を解きます。",
        "user": "UL1HFJATE",
        "type": "message"
    },
    {
        "ts": "1598167369.004000",
        "text": "実装でこんがらがっている :exploding_head:",
        "user": "U4L0B71L1",
        "type": "message"
    },
    {
        "ts": "1598167892.005600",
        "text": "わたしもSlackのAPIがメッセージを返す順番が、古いものと新しいものとで逆なんでこんがらがりました... :exploding_head:\n多分もう大丈夫",
        "user": "U4LGTMTMK",
        "type": "message"
    },
    {
        "ts": "1598168595.005800",
        "text": "<@U019BASD7D0> has joined the channel",
        "user": "U019BASD7D0",
        "type": "message"
    },
    {
        "ts": "1598169362.007700",
        "text": "最近の開発に疎いですが参加しました。よろしくお願いします。",
        "user": "U019BASD7D0",
        "type": "message"
    },
    {
        "ts": "1598169451.008900",
        "text": "ようこそ！残り時間は短いですが何か相談したくなったらいつでも聞いてください！\n（今日は諸般の事情によりビデオチャットのルームは用意しておりません... あしからず。）",
        "user": "U4LGTMTMK",
        "type": "message"
    },
    {
        "ts": "1598170403.014100",
        "text": "ADWH Ch 1. Exercises  オワタ　　後半１／４はかなり難しい　答えが付いているので助かる　1.16 Fusion rule 入力が bottom の話は消化不良　ではまた",
        "user": "U584T7GAH",
        "type": "message"
    },
    {
        "ts": "1598171261.015000",
        "text": "私ももくdevの方が終了したので一旦引き上げます。",
        "user": "U4LGTMTMK",
        "type": "message"
    },
    {
        "ts": "1598173204.015300",
        "text": "Reminder: 成果報告のお時間です！\nしたことを共有しましょう",
        "user": "USLACKBOT",
        "type": "message"
    },
    {
        "ts": "1598173465.016200",
        "text": "Haskell インタープリター、根本のデータ構造の変更をしてたのですがやっぱりダメっぽい気がしてきて悩む時間でした",
        "user": "U4L0B71L1",
        "type": "message"
    },
    {
        "ts": "1598173858.017500",
        "text": "<!here> 次回運営してくれる人がいたら :raising_hand: お願いしますー！",
        "user": "U4L0B71L1",
        "type": "message"
    },
    {
        "ts": "1598175008.021400",
        "text": "TLEを乗り越えてEまで解きました。Bang Patternの有無によって、最適化の関係で実行時間オーダーが変化するという稀有な体験をしました。",
        "user": "UL1HFJATE",
        "type": "message"
    },
    {
        "ts": "1598175467.026900",
        "text": "報告漏れてました。前回より引き続きconversations.repliesというSlackのWeb APIを連続して呼んでスレッドのメッセージを全部取得する関数を修正してました。\n修正前にも似た関数があったので再利用していたのですが、どうも使いづらいので一から再実装したほうが良さそうです:cold_sweat:",
        "user": "U4LGTMTMK",
        "type": "message"
    },
    {
        "ts": "1598175547.027100",
        "text": "私は次回だと日曜日ならフルで参加できます。",
        "user": "U4LGTMTMK",
        "type": "message"
    },
    {
        "ts": "1598176424.027400",
        "text": "来週は厳しそうです :pray:",
        "user": "U4KPPQW7K",
        "type": "message"
    },
    {
        "ts": "1598179902.027700",
        "text": "明日まで待ってみて反応なければいつものメンバーにメンションします",
        "user": "U4L0B71L1",
        "type": "message"
    },
    {
        "ts": "1598311527.028700",
        "text": "で、どうしましょう？順番的には\n<@U59TQ3MJ9> さんが最後にやったのが7/24なので一番日が空きますがご都合いかがでしょうか？",
        "user": "U4LGTMTMK",
        "type": "message"
    },
    {
        "ts": "1598313264.028900",
        "text": "（昨日寝ちゃった、今書こうと思ったら先を越されてしまった",
        "user": "U4L0B71L1",
        "type": "message"
    }
]