[
    {
        "text": "<@U02E1JRGKEK> has joined the channel",
        "type": "message",
        "ts": "1631683142.000800",
        "user": "U02E1JRGKEK"
    },
    {
        "text": "<@U02FHKCM32M> has joined the channel",
        "type": "message",
        "ts": "1632233948.001000",
        "user": "U02FHKCM32M"
    },
    {
        "text": "連投申し訳ありません。高次元圏をHaskellで実現することはできますか？\n3-cellなどの実装もできるのでしょうか。",
        "type": "message",
        "ts": "1633320879.001200",
        "user": "UFMV026NR"
    },
    {
        "text": "<@U02G96VNDFG> has joined the channel",
        "type": "message",
        "ts": "1634369392.026400",
        "user": "U02G96VNDFG"
    },
    {
        "text": "読むかどうかは未定ですが興味ある方もいらっしゃるでしょうし共有します\n<https://twitter.com/hora_algebra/status/1456866087400738819?s=20|https://twitter.com/hora_algebra/status/1456866087400738819?s=20>",
        "type": "message",
        "ts": "1636280991.001400",
        "user": "U4LGTMTMK"
    },
    {
        "text": "キマイラ飼育記が Lens を取り上げました！\n<https://m-hiyama.hatenablog.com/entry/2021/11/12/112110>",
        "type": "message",
        "ts": "1636686993.002700",
        "user": "U5LEE6C1J"
    },
    {
        "text": "「ziplist monad proof」でググったら Ziplist アプリカティブがモナドにならないことの証明と思われる Coqコードを見つけた。\n<https://gist.github.com/viercc/38853067c893f7ad9e0894abb543178b> （こちらは日本の人のだ）\n<https://gist.github.com/Lysxia/b105bcb2f2ba835012476ab7fe37ae87>",
        "type": "message",
        "ts": "1636878256.005900",
        "user": "U57CGDBMG"
    },
    {
        "text": "<@U02M9636PFV> has joined the channel",
        "type": "message",
        "ts": "1636940685.006700",
        "user": "U02M9636PFV"
    },
    {
        "text": "<@U02NV1XHYBT> has joined the channel",
        "type": "message",
        "ts": "1637750173.007800",
        "user": "U02NV1XHYBT"
    },
    {
        "text": "<@U02D4U38VA8> has joined the channel",
        "type": "message",
        "ts": "1638449997.008200",
        "user": "U02D4U38VA8"
    },
    {
        "text": "<@U02P4JW563Z> has joined the channel",
        "type": "message",
        "ts": "1638711441.008400",
        "user": "U02P4JW563Z"
    },
    {
        "text": "今ちょっと気になったのですが、Haskellの型と関数の「圏」Hask って、\n`f: a → b, g: b → c` に対して、\n\n```f &gt;&gt;&gt; g =  f `seq` g `seq` \\x -&gt; g (f x)```\nで定義すると本物の圏ですか？",
        "type": "message",
        "ts": "1639147160.009500",
        "user": "UL1HFJATE"
    },
    {
        "text": "<@U02KK6NUFFE> has joined the channel",
        "type": "message",
        "ts": "1639656618.020600",
        "user": "U02KK6NUFFE"
    },
    {
        "text": "<@U015L5JEP8D> has joined the channel",
        "type": "message",
        "ts": "1639976923.020800",
        "user": "U015L5JEP8D"
    },
    {
        "text": "この問題なんですが、タプルを正格にするとモノイド圏にならないのが非常にネックなんですよね",
        "type": "message",
        "ts": "1640801182.020900",
        "user": "U570660KX"
    },
    {
        "text": "<@U02S5NRT8QL> has joined the channel",
        "type": "message",
        "ts": "1641254268.024800",
        "user": "U02S5NRT8QL"
    },
    {
        "text": "個人事業主になったので、重い腰を上げて複式簿記を調べてるんですが、複式簿記の仕訳を行列で表現すると「自由加群」になるとかで、こっち方面から理解したい\n<https://keito.luxe/2019/05/03/matrix-bookkeeping/|https://keito.luxe/2019/05/03/matrix-bookkeeping/>",
        "type": "message",
        "ts": "1642059600.002300",
        "user": "U4L0B71L1"
    },
    {
        "text": "勘定科目のペア `(借方の勘定科目, 貸方の勘定科目)` の集合を基底とする自由 ℕ-加群と思えばいいんでしょうか。100円のものを買ったことは `100 (消耗品費, 現金)` と表すような。",
        "type": "message",
        "ts": "1642067305.006800",
        "user": "U578W9676"
    },
    {
        "text": "<@U02TZTH6VMZ> has joined the channel",
        "type": "message",
        "ts": "1642117080.007000",
        "user": "U02TZTH6VMZ"
    },
    {
        "text": "こんにちは！\nTwitterで私の記事がこちらのチャンネルで取り上げられていると伺いまして、是非仲間に入れてほしいと思い参加させていただきました。\nよろしくお願いいたします。",
        "type": "message",
        "ts": "1642117153.008900",
        "user": "U02TZTH6VMZ"
    },
    {
        "text": "<@U02UPKJ4072> has joined the channel",
        "type": "message",
        "ts": "1642117721.009200",
        "user": "U02UPKJ4072"
    },
    {
        "text": "<@UHSDG4H2P> has joined the channel",
        "type": "message",
        "ts": "1642209992.011100",
        "user": "UHSDG4H2P"
    },
    {
        "text": "<@U02TL2WEM7H> has joined the channel",
        "type": "message",
        "ts": "1642468843.011500",
        "user": "U02TL2WEM7H"
    },
    {
        "text": "<@U02U62Z90LS> has joined the channel",
        "type": "message",
        "ts": "1642949981.011800",
        "user": "U02U62Z90LS"
    },
    {
        "text": "<@U02USQMELUX> has joined the channel",
        "type": "message",
        "ts": "1643124757.369319",
        "user": "U02USQMELUX"
    },
    {
        "text": "<@U030SJVBYLT> has joined the channel",
        "type": "message",
        "ts": "1643590126.623409",
        "user": "U030SJVBYLT"
    },
    {
        "text": "<@UGQGVSB4L> has joined the channel",
        "type": "message",
        "ts": "1643683450.552869",
        "user": "UGQGVSB4L"
    },
    {
        "text": "<@UA68LF694> has joined the channel",
        "type": "message",
        "ts": "1647332733.379039",
        "user": "UA68LF694"
    },
    {
        "text": "<@U038R6FM96G> has joined the channel",
        "type": "message",
        "ts": "1648205108.462629",
        "user": "U038R6FM96G"
    },
    {
        "text": "<@U03ATB52EHW> has joined the channel",
        "type": "message",
        "ts": "1652619020.812009",
        "user": "U03ATB52EHW"
    }
]