[
    {
        "ts": "1629685901.031100",
        "text": "つい最近更新されたようなので。定期的に共有したいですねー。\n<https://github.com/takenobu-hs/haskell-symbol-search-cheatsheet>",
        "user": "U4LGTMTMK",
        "type": "message"
    },
    {
        "ts": "1630145482.001700",
        "text": "スレッドの追加テスト",
        "user": "U4LGTMTMK",
        "type": "message"
    },
    {
        "ts": "1630145484.001900",
        "text": "スレッドの追加テスト2",
        "user": "U4LGTMTMK",
        "type": "message"
    },
    {
        "ts": "1630145753.002100",
        "text": "バッチリ生成できたようです！ :relieved:",
        "user": "U4LGTMTMK",
        "type": "message"
    },
    {
        "ts": "1630190163.002500",
        "text": ":man-bowing: すみません、文脈を共有してませんでした。\nslack-logのこちらの修正 <https://github.com/haskell-jp/slack-log/pull/58> の、リリース後の確認をしていました。",
        "user": "U4LGTMTMK",
        "type": "message"
    }
]