[
    {
        "ts": "1575558891.164400",
        "text": "いまいち INLINE 付けるべき勘所が分からない\nINLINE 付けないとモジュールを越えた融合変換が効かないというのは users' guide で知ったけど",
        "user": "U4L0B71L1",
        "type": "message"
    },
    {
        "ts": "1575591731.165000",
        "text": "<http://Haskell.org|Haskell.org> committeeのメンバーを募集しています\n<https://www.reddit.com/r/haskell/comments/e6qcsf/call_for_haskellorg_committee_nominations/>",
        "user": "U4M9NJ7QE",
        "type": "message"
    },
    {
        "ts": "1575594294.165300",
        "text": "お疲れ様でした！ :tada:\n単純な興味本位で恐縮ですが、maoeさんはやってみてどうでした？",
        "user": "U4LGTMTMK",
        "type": "message"
    },
    {
        "ts": "1575595547.165500",
        "text": "一番大がかりな仕事はGoogle Summer of Code/Summer of Haskellなんですが、初年度は引き継ぎのタイミングで上手くいかなかったのを反省して、ここ数年は上手くいくようになったのは良かったです。コミュニケーションもIRCだったのをSlackに変えたり、ドキュメントやGSoC関連のタスクをGitHub for non-profitに移したり環境も整備され快適になっています。\n当初は日本のコミュニティと英語圏のコミュニティの架け橋になるような活動をもっとしたかったんですが、プライベートが忙しくなって全然時間が割けなくなったので結局あまり出来なかったのが残念です。",
        "user": "U4M9NJ7QE",
        "type": "message"
    },
    {
        "ts": "1575604255.165900",
        "text": "すみません、どんなお仕事なのか、まだ完全にイメージがわかないです。\n<https://wiki.haskell.org/Haskell.org_committee> を読む限り\n<http://haskell.org|haskell.org> の運営が主なところなんですかね？",
        "user": "U4LGTMTMK",
        "type": "message"
    },
    {
        "ts": "1575605075.166100",
        "text": "<https://github.com/sol/doctest/issues/245> doctestはcabal v2-buildに対応してない（？）みたいですね",
        "user": "UGM9F7XQS",
        "type": "message"
    },
    {
        "ts": "1575605256.166400",
        "text": "• GSoC/HoSの運営\n• haskell.org配下のサービスの運用ポリシーを決める（e.g. &lt;http://discourse.haskell.org|discourse.haskell.org&gt;）\n• 寄付金の受領・管理・効果的な使途の模索\n• 会計報告\n• コミュニティ内の問題解決\n• オフライン(ICFP etc)・オンラインでのミーティング",
        "user": "U4M9NJ7QE",
        "type": "message"
    },
    {
        "ts": "1575605286.166700",
        "text": "あたりでしょうか",
        "user": "U4M9NJ7QE",
        "type": "message"
    },
    {
        "ts": "1575605338.166900",
        "text": "仕事量的にはGSoCがメインになります",
        "user": "U4M9NJ7QE",
        "type": "message"
    },
    {
        "ts": "1575605880.167100",
        "text": "これ doctest だからか\nv2-build では cabal-doctest を使うと聞きましたね",
        "user": "U4L0B71L1",
        "type": "message"
    },
    {
        "ts": "1575606100.167600",
        "text": "GSoCの運営っていうのは、参加者のmentorとかですかね？",
        "user": "U4LGTMTMK",
        "type": "message"
    },
    {
        "ts": "1575606472.167800",
        "text": "メンターは別に募集します。運営側はアイデアを募集してプロジェクトのリストとしてまとめgoogleに提出して審査が通ると始めて組織としてgsocに参加できるようになります。その後、参加者を募集して選考を行い、メンターともマッチングさせた後、実際のプロジェクトが始まります。\nその後も中間報告のとりまとめと、中間評価でpass/failの判断をしたり、最終報告と評価のとりまとめ等もします。",
        "user": "U4M9NJ7QE",
        "type": "message"
    },
    {
        "ts": "1575606512.168000",
        "text": "組織としてgsocの選考に落ちるとsummer of haskellとして自分たちで金策等もするのでさらにやることが増えます",
        "user": "U4M9NJ7QE",
        "type": "message"
    },
    {
        "ts": "1575606641.168400",
        "text": "ありがとうございます！割とイメージがわきました！",
        "user": "U4LGTMTMK",
        "type": "message"
    },
    {
        "ts": "1575606680.168600",
        "text": "&lt;https://google.github.io/gsocguides/mentor/&gt; ここのOrg Admin のところが &lt;http://Haskell.org|Haskell.org&gt; committeeの担当に相当します",
        "user": "U4M9NJ7QE",
        "type": "message"
    },
    {
        "ts": "1575628447.173800",
        "text": "ディレクトリのパスとファイルのパスを受け取って、前者の下に後者が含まれているかどうか判定する (foo “foo/“ “foo/baa/a.txt” の時も True) 、絶対パスにも対応している関数って意外とないんですね",
        "user": "U5LEE6C1J",
        "type": "message"
    }
]