[
    {
        "ts": "1587976027.246300",
        "text": "むぅ",
        "user": "U5G2BCVBN",
        "type": "message"
    },
    {
        "ts": "1587976279.246600",
        "text": "ghcideだとある程度補完も動くので(ある程度止まりですが…)やはりまだhlsじゃなくてghcideを使うべきなようですね\n情報ありがとうございます",
        "user": "U57CUMWQ6",
        "type": "message"
    },
    {
        "ts": "1587976816.246900",
        "text": "<@U012KLD4SSW> has joined the channel",
        "user": "U012KLD4SSW",
        "type": "message"
    },
    {
        "ts": "1587985379.247100",
        "text": "ghcidは mkMessage で作ったメッセージをなかなか参照してくれなくてつらいということもわかってきました…",
        "user": "U57CUMWQ6",
        "type": "message"
    },
    {
        "ts": "1587993443.247900",
        "text": "プロダクション用などでハードに使う観点からは物足りないかもしれませんが、裾野を広げる観点でカジュアルな緩い記事を書きました:haskell:\n「Haskellを業務で使う、カジュアルに」\n<https://haskell.jp/blog/posts/2020/haskell-casually-at-work.html>",
        "user": "U55V441FS",
        "type": "message"
    },
    {
        "ts": "1588032035.248900",
        "text": "575なの気づかなかった... <https://b.hatena.ne.jp/entry/s/haskell.jp/blog/posts/2020/haskell-casually-at-work.html>",
        "user": "U4LGTMTMK",
        "type": "message"
    },
    {
        "ts": "1588081907.249300",
        "text": "おぉ、本人が気づいてなかった:exclamation:",
        "user": "U55V441FS",
        "type": "message"
    },
    {
        "ts": "1588203481.251100",
        "text": "stackのver. 2.3.1がでました！ :tada:\nバイナリパッケージでリリースされるプラットフォームが減り、Linux版などをダウンロードするURLが変わったのでスクリプトでダウンロードしている人は気をつけろ、と。\n<https://github.com/commercialhaskell/stack/releases/tag/v2.3.1>",
        "user": "U4LGTMTMK",
        "type": "message"
    },
    {
        "ts": "1588242768.251800",
        "text": "<https://twitter.com/public_ai000ya/status/1255807194924109824?s=19|https://twitter.com/public_ai000ya/status/1255807194924109824?s=19>",
        "user": "U5LV76EJH",
        "type": "message"
    },
    {
        "ts": "1588242808.252200",
        "text": "あれま……",
        "user": "U5LV76EJH",
        "type": "message"
    },
    {
        "ts": "1588308546.253100",
        "text": "Redditからです。 Wisconsin大学での、HaskellとRustの講座です。\nこの時期にゆっくり思索するのにも良いかと。\n\nCS 538: Theory and Design of Programming Languages (Spring 2020)\n<https://pages.cs.wisc.edu/~justhsu/teaching/current/cs538/calendar/>\n\nReddit記事\n<https://www.reddit.com/r/haskell/comments/gb1gx4/uwisconsin_course_on_haskell_and_rust/>",
        "user": "U55V441FS",
        "type": "message"
    },
    {
        "ts": "1588318535.254200",
        "text": "Egisonのパターンマッチを50ページほどで解説するチュートリアル資料「プログラミング言語Egison入門」を公開しました．\nぜひ読んでみてください！\n<http://egison.org/tutorial.pdf|egison.org/tutorial.pdf>",
        "user": "U80GXHF6Y",
        "type": "message"
    },
    {
        "ts": "1588335407.256500",
        "text": "ArchWSLを使ってる方がどのくらいいるのかわからないんですが、このissueについて何かしら知ってる方いますか？\nxmonadがコンパイルできなくってお亡くなりに…\n<https://gitlab.haskell.org/ghc/ghc/issues/17918>",
        "user": "ULTBB86UC",
        "type": "message"
    },
    {
        "ts": "1588339300.256900",
        "text": "強力なパターンマッチはほしいのですが\nパターンの網羅性や冗長性の確認はできますか？\nどこかで研究課題としてあがっていたとおもいましたので。",
        "user": "U74KTAG0N",
        "type": "message"
    },
    {
        "ts": "1588339466.257300",
        "text": "あまり気にしなくていいのならそれでもいいのですが。",
        "user": "U74KTAG0N",
        "type": "message"
    },
    {
        "ts": "1588382061.258000",
        "text": "今年は ICFP 2020 もオンラインになるようです:earth_americas:\n<https://icfp20.sigplan.org/>\n\n別件で、ZuriHac (スイスで行われる大きなHackathon)もオンラインで行われるとのことです:haskell:\n<https://zfoh.ch/zurihac2020/>",
        "user": "U55V441FS",
        "type": "message"
    },
    {
        "ts": "1588385035.258800",
        "text": "8月予定の新書籍です。著者からして期待大:book::lion_face:\n\nAlgorithm Design with Haskell\n<https://www.cambridge.org/core/books/algorithm-design-with-haskell/824BE0319E3762CE8BA5B1D91EEA3F52#>",
        "user": "U55V441FS",
        "type": "message"
    },
    {
        "ts": "1588388677.259200",
        "text": "パターンの網羅性や冗長性の確認はまだできていないです．もしするとしたら，網羅性のチェックがしやすいように，パターンの書き方に制限を加えた上で考えることになりそうだと思っています．",
        "user": "U80GXHF6Y",
        "type": "message"
    },
    {
        "ts": "1588390154.259900",
        "text": ":bird: 先生が :lion_face: が表紙の本を書くと！",
        "user": "U4LGTMTMK",
        "type": "message"
    },
    {
        "ts": "1588396588.260200",
        "text": "<@U012WHCBRSR> has joined the channel",
        "user": "U012WHCBRSR",
        "type": "message"
    },
    {
        "ts": "1588400929.260500",
        "text": "<@U012R7RMZB8> has joined the channel",
        "user": "U012R7RMZB8",
        "type": "message"
    },
    {
        "ts": "1588456424.261600",
        "text": "<@U012YCXSY90> has joined the channel",
        "user": "U012YCXSY90",
        "type": "message"
    },
    {
        "ts": "1588509286.262000",
        "text": "こういうの直接こっちにも投げてくれると楽しい <https://twitter.com/public_ai000ya/status/1256915989133811714>",
        "user": "U4LGTMTMK",
        "type": "message"
    },
    {
        "ts": "1588509472.262400",
        "text": "RecordDotSyntax Acceptされたんですね :clap:",
        "user": "U4KPPQW7K",
        "type": "message"
    },
    {
        "ts": "1588586990.263900",
        "text": "趣味でですがこんな物を作りました :speaker:\nバックエンドのWebSocketsで通信してるところをHaskellで書いてます-!\n<https://twitter.com/lotz84_/status/1257224385536000000>",
        "user": "U4KPPQW7K",
        "type": "message"
    },
    {
        "ts": "1588588107.264200",
        "text": "これは英語版READMEを用意して Redditへ貼るのが良いのでは:sunny::haskell:\n（まだ時期尚早？）",
        "user": "U55V441FS",
        "type": "message"
    },
    {
        "ts": "1588588390.264400",
        "text": "もうちょっと開発が進んだらそれも良いですね!\n今は周りの人からフィードバックもらいたいなと思って日本語で書いてます :smile:",
        "user": "U4KPPQW7K",
        "type": "message"
    },
    {
        "ts": "1588647485.265800",
        "text": "<@U0131S18PGT> has joined the channel",
        "user": "U0131S18PGT",
        "type": "message"
    },
    {
        "ts": "1588700153.266300",
        "text": "<@U012NFZ34S3> has joined the channel",
        "user": "U012NFZ34S3",
        "type": "message"
    },
    {
        "ts": "1588743280.267500",
        "text": ":confetti_ball: :sunny: :confetti_ball: Google Summer of CodeとしてHaskell.orgが採択したプロジェクトが決まりました\n<https://summerofcode.withgoogle.com/organizations/6387985961975808/>",
        "user": "U4LGTMTMK",
        "type": "message"
    },
    {
        "ts": "1588822924.271400",
        "text": "多相レコードのブログ記事、初心者向けの体で書こうと思ったんですが、\nlensでやると記号がエグくて初心者バイバイ感半端ないという問題が発覚\n\n```main = do\n    let p = Person { name = \"Taro\", age = 10 }\n\n    -- レコード要素へのアクセス\n    print $ p ^. #name\n\n    -- レコード要素への代入\n    print $ p &amp; #age .~ 11```\n初心者に勧めるのはRecordDotSyntaxを待った方が良いかも……",
        "user": "U570660KX",
        "type": "message"
    },
    {
        "ts": "1588823138.271600",
        "text": "`RecordDotSyntax` が普及したらその紹介事態が「最新多相レコード事情」になりますねw\n個人的には初心者向けは端から諦めるか、軽く背景を注釈しつつ「表層的な構文なんて飾りだよ？」って考えを受け入れられる人をターゲットにするべきかと。",
        "user": "U4LGTMTMK",
        "type": "message"
    },
    {
        "ts": "1588824235.271800",
        "text": "慣れてしまうとlensの書き方も読みやすいと感じてしまうのもまた罠ですね :sweat_smile:",
        "user": "U4KPPQW7K",
        "type": "message"
    },
    {
        "ts": "1588824331.272300",
        "text": "使いづらいシステムにも人間は順応しちゃいますからね... :cold_sweat:",
        "user": "U4LGTMTMK",
        "type": "message"
    },
    {
        "ts": "1588824427.272500",
        "text": "lens、初心者にとって辛いのはシンタックスのほかにもあって、型エラーになったときの対処なんですね。\n型推論のストーリーくらいは紹介しないといけなくて、どうしても中級者以上になってしまう",
        "user": "U570660KX",
        "type": "message"
    },
    {
        "ts": "1588824844.273000",
        "text": "ではlensじゃなくて、普通に `#age :: Person -&gt; Int` になるIsLabelインスタンスを使う、というのも手なのですが、 現状 `instance (HasField x r a) =&gt; IsLabel x (r -&gt; a)` のインスタンス定義がない。\n各自が勝手にOrphan Instanceを定義すると、他と被ったときに死ぬので xxx-orphans みたいなライブラリが欲しい",
        "user": "U570660KX",
        "type": "message"
    },
    {
        "ts": "1588832383.273600",
        "text": "lensに関しては演算子よりもアルファベットの名前のついた関数（viewやset）を使ったほうが初心者に優しいような気がします",
        "user": "UGM9F7XQS",
        "type": "message"
    },
    {
        "ts": "1588907039.274800",
        "text": "これはとっても期待したい :up:\n<https://github.com/ghc-proposals/ghc-proposals/pull/330>",
        "user": "U4LGTMTMK",
        "type": "message"
    },
    {
        "ts": "1588939840.275500",
        "text": "ここでnand2tetris知ったのですが、Haskellでコンパイラ作りました。めちゃくちゃ面白かったです！\n難易度とテストの並びが絶妙で0から実装したものが動く感じがよかったです。\nsatunさん、mitsuchiさんありがとうございました！",
        "user": "UG8CPC0L8",
        "type": "message"
    }
]