[
    {
        "ts": "1604712010.147500",
        "text": "以前に話のあった、prime関連のWebページの在り処についてです。 TracからGitLabへの移行に伴って、以下の場所にmigrateされていましたので共有しておきます。\n<https://gitlab.haskell.org/haskell/prime/-/wikis/home>\nなお、3-release-policyのページは以下です。\n<https://gitlab.haskell.org/haskell/prime/-/wikis/libraries/3-release-policy>\n（あと、タイトルindexページを追加したので、そのうち各ページが、Google検索などの対象になると思います。）",
        "user": "U55V441FS",
        "type": "message"
    },
    {
        "ts": "1604720450.148100",
        "text": "<@U01EEFP2KT6> has joined the channel",
        "user": "U01EEFP2KT6",
        "type": "message"
    },
    {
        "ts": "1604731271.148500",
        "text": "<@U01E1MFRX8E> has joined the channel",
        "user": "U01E1MFRX8E",
        "type": "message"
    },
    {
        "ts": "1604977000.148800",
        "text": "<@U01ED8J2PQB> has joined the channel",
        "user": "U01ED8J2PQB",
        "type": "message"
    },
    {
        "ts": "1605066217.149000",
        "text": "<@U01EV0SRHPT> has joined the channel",
        "user": "U01EV0SRHPT",
        "type": "message"
    },
    {
        "ts": "1605148192.149800",
        "text": "久々にRedditのタイムラインを見てみたらhaskell-language-server-0.6.0が出てた <https://www.reddit.com/r/haskell/comments/jsfq35/ann_haskelllanguageserver060_has_been_released/>",
        "user": "U4LGTMTMK",
        "type": "message"
    },
    {
        "ts": "1605164252.150100",
        "text": "hieでは動いてたhlint統合動かないなーと思ってたら動くようになったんですね\nこれはうれしい",
        "user": "U57CUMWQ6",
        "type": "message"
    },
    {
        "ts": "1605334722.151100",
        "text": "<@U01EJPV0E2J> has joined the channel",
        "user": "U01EJPV0E2J",
        "type": "message"
    }
]