[
    {
        "text": "<@U02RB7KA56Y> has joined the channel",
        "type": "message",
        "ts": "1639806629.217300",
        "user": "U02RB7KA56Y"
    },
    {
        "text": "超小物パッケージです。`exitSuccess` 関数を `IO` 以外のMonadから呼ぶためだけに作りました。\n<https://hackage.haskell.org/package/monad-throw-exit>",
        "type": "message",
        "ts": "1639807805.218100",
        "user": "U4LGTMTMK"
    },
    {
        "text": "github action で CI を回すときの注意：\n• macos-latest だと hspec がハングする。macOS-10.15 を使うべし\n• GHC '8.10' で使われる 8.10.2 は Windows ではリンカーのバグがある。'8.8'を使うべし\nこのせいで、一日損した。",
        "type": "message",
        "ts": "1639956829.219000",
        "user": "U56MBRKR9"
    },
    {
        "text": "<@U02RQ8E76DP> has joined the channel",
        "type": "message",
        "ts": "1639977076.219600",
        "user": "U02RQ8E76DP"
    },
    {
        "text": "&gt; 今までは、どの OS であれ `ghc-X.Y.Z` のようなディレクトリ名でした。しかし、9.2.1 の Windows と Mac、9.0.1 の Windows は（なぜか）`ghc-9.2.1-x86_64-apple-darwin` のような `tar.xz` ファイル名になっていました。仕方がないので、GHC のバージョンと OS によってディレクトリ名が変わるように修正しました:\n&gt; <https://matsubara0507.github.io/posts/2021-12-20-fix-rules_haskell-for-ghc_9_2_1.html> by <@U56L7EVNY> \n分かる…… これなんで変わったのかな\nghcman でもこの対応入れた\n<https://github.com/kakkun61/ghcman/blob/master/version.yaml>\nCabal も 3.4 からパスの命名規則変わったんすよね",
        "type": "message",
        "ts": "1639981418.221400",
        "user": "U4L0B71L1"
    },
    {
        "text": "<@U02RZNLGUV7> has joined the channel",
        "type": "message",
        "ts": "1640130779.222900",
        "user": "U02RZNLGUV7"
    },
    {
        "text": "こいつぁビッグなクリスマスプレゼント :gift:\n<https://discourse.haskell.org/t/text-2-0-with-utf8-is-finally-released/3840>",
        "type": "message",
        "ts": "1640412770.223800",
        "user": "U4LGTMTMK"
    },
    {
        "text": "igrepさんのHaskell-jp記事:sparkles:に合わせて、私の記号検索記事の日本語版も久々に更新しました。\n(Qiitaはメンテナンスせず塩漬けにしてたので)お試しがてら以下のZennに記事を移しました。\n<https://zenn.dev/takenobu_hs/articles/384ea7b5c09ee4>",
        "type": "message",
        "ts": "1640424452.226100",
        "user": "U55V441FS"
    },
    {
        "text": "記号リファレンス、そういえば何か足りないと思って何だったっけな……",
        "type": "message",
        "ts": "1640450956.227800",
        "user": "U4L0B71L1"
    },
    {
        "text": "<@U02RVSD1XC5> has joined the channel",
        "type": "message",
        "ts": "1640473346.228100",
        "user": "U02RVSD1XC5"
    },
    {
        "text": "GHC 9.0.2がリリースされたようです。 AArch64の大きな不具合が直っているとのことです:christmas_tree:\n<https://www.haskell.org/ghc/blog/20211225-ghc-9.0.2-released.html>",
        "type": "message",
        "ts": "1640478094.228500",
        "user": "U55V441FS"
    },
    {
        "text": "<@U02SP3AHZEC> has joined the channel",
        "type": "message",
        "ts": "1640526502.229900",
        "user": "U02SP3AHZEC"
    },
    {
        "text": "<@U02RKUT28TH> has joined the channel",
        "type": "message",
        "ts": "1640592968.230300",
        "user": "U02RKUT28TH"
    },
    {
        "text": "<@U02S5NRT8QL> has joined the channel",
        "type": "message",
        "ts": "1640678102.230600",
        "user": "U02S5NRT8QL"
    },
    {
        "text": "<@U02S0UVRQH3> has joined the channel",
        "type": "message",
        "ts": "1640688275.230800",
        "user": "U02S0UVRQH3"
    },
    {
        "text": "<@U02RPSLC4MV> has joined the channel",
        "type": "message",
        "ts": "1640702922.231000",
        "user": "U02RPSLC4MV"
    },
    {
        "text": "<@U02S6LB73C2> has joined the channel",
        "type": "message",
        "ts": "1640767554.231200",
        "user": "U02S6LB73C2"
    },
    {
        "text": "ghcupにGHC 9.0.2が降ってこないと思ったらメンテナのパソコンが修理中で署名ができない状態だそうです <https://github.com/haskell/ghcup-metadata/issues/12|https://github.com/haskell/ghcup-metadata/issues/12>",
        "type": "message",
        "ts": "1641050509.235000",
        "user": "UGM9F7XQS"
    },
    {
        "text": "<@U02RZTDNVFH> has joined the channel",
        "type": "message",
        "ts": "1641085373.235700",
        "user": "U02RZTDNVFH"
    },
    {
        "text": "<@U02T0K000AV> has joined the channel",
        "type": "message",
        "ts": "1641308127.236400",
        "user": "U02T0K000AV"
    },
    {
        "text": "ghcupにGHC 9.0.2が降ってきたようです",
        "type": "message",
        "ts": "1641379839.237100",
        "user": "UGM9F7XQS"
    },
    {
        "text": "GHCでも、moldリンカ対応が徐々に始まってるみたいです。 GHCでのビルドが速くなっていくと良いですね:sparkles:\n<https://gitlab.haskell.org/ghc/ghc/-/merge_requests/7296>",
        "type": "message",
        "ts": "1641694059.000900",
        "user": "U55V441FS"
    },
    {
        "text": "暗号化関連のライブラリーのメンテナンスを、Haskell Foundationとして専用のGitHub Orgを使ってサポートすることに。参加者募集\n<https://discourse.haskell.org/t/a-new-future-for-cryptography-in-haskell/3888?utm_source=pocket_mylist>",
        "type": "message",
        "ts": "1641890625.003200",
        "user": "U4LGTMTMK"
    },
    {
        "text": "恐らくというかほぼ間違いなく背景はこのあたりの話でしょう: <https://haskell.jp/slack-log/html/C4M4TT8JJ/88.html#message-1615767559.015900>",
        "type": "message",
        "ts": "1641891263.003800",
        "user": "U4LGTMTMK"
    },
    {
        "text": "<https://github.com/haskell-cryptography/cryptonite-cd>\ncd ってサフィックスは何を意味しているんだろか :thinking_face:",
        "type": "message",
        "ts": "1641892208.004500",
        "user": "U56L7EVNY"
    },
    {
        "text": "community-driven?",
        "type": "message",
        "ts": "1641892408.005000",
        "user": "UK0MXUCAV"
    },
    {
        "text": "<@U02TPLXSZQC> has joined the channel",
        "type": "message",
        "ts": "1641949461.005900",
        "user": "U02TPLXSZQC"
    },
    {
        "text": "<@U02TZTH6VMZ> has joined the channel",
        "type": "message",
        "ts": "1642116955.006500",
        "user": "U02TZTH6VMZ"
    },
    {
        "text": "<@U02UPKJ4072> has joined the channel",
        "type": "message",
        "ts": "1642117412.006700",
        "user": "U02UPKJ4072"
    },
    {
        "text": "マジか。知らなかった。 <https://twitter.com/mattn_jp/status/1478628274524012545>",
        "type": "message",
        "ts": "1642126327.007000",
        "user": "U4LGTMTMK"
    },
    {
        "text": "<@U02TL2WEM7H> has joined the channel",
        "type": "message",
        "ts": "1642135996.007900",
        "user": "U02TL2WEM7H"
    },
    {
        "text": "Haskell公式のDockerイメージが、arm64(AArch64)にも対応したとのことです。\nx86版と違って、GHC + cabal が入っています(stackは未だ入ってない)。\n<https://discourse.haskell.org/t/haskell-official-docker-images-now-support-arm64-and-other-updates/3917>\n<https://hub.docker.com/_/haskell>",
        "type": "message",
        "ts": "1642208856.008400",
        "user": "U55V441FS"
    },
    {
        "text": "<@U02U60B3WSX> has joined the channel",
        "type": "message",
        "ts": "1642217153.009000",
        "user": "U02U60B3WSX"
    },
    {
        "text": "<@U02U8AFNSUU> has joined the channel",
        "type": "message",
        "ts": "1642221727.009300",
        "user": "U02U8AFNSUU"
    },
    {
        "text": "<@U02U62Z90LS> has joined the channel",
        "type": "message",
        "ts": "1642224776.009500",
        "user": "U02U62Z90LS"
    },
    {
        "text": "<@U02V9F3MWS0> has joined the channel",
        "type": "message",
        "ts": "1642934917.018400",
        "user": "U02V9F3MWS0"
    },
    {
        "text": "<@U02USQMELUX> has joined the channel",
        "type": "message",
        "ts": "1642950751.018600",
        "user": "U02USQMELUX"
    },
    {
        "text": "<@U02V92FG4V8> has joined the channel",
        "type": "message",
        "ts": "1643010640.018800",
        "user": "U02V92FG4V8"
    },
    {
        "text": "<@U030QRD01TK> has joined the channel",
        "type": "message",
        "ts": "1643230408.394879",
        "user": "U030QRD01TK"
    },
    {
        "text": "<@U030SJVBYLT> has joined the channel",
        "type": "message",
        "ts": "1643446314.880609",
        "user": "U030SJVBYLT"
    },
    {
        "text": "なかなか辛辣な内容。。。\n\"What killed Haskell, could kill Rust, too\"\n<https://gist.github.com/graninas/22ab535d2913311e47a742c70f1d2f2b>",
        "type": "message",
        "ts": "1643530459.011629",
        "user": "U56MBRKR9"
    }
]