[
    {
        "ts": "1715258221.498639",
        "text": "Core to Hsあるいは、Core to sourceする関数ってありますか？ GHC APIの中に見つからなかったのですが\n\n今私は、Coreの型からCoreExprを計算する <https://hackage.haskell.org/package/ghc-9.8.2/docs/GHC-Tc-Errors-Hole.html#t:HoleFitPlugin|HoleFitPlugin>を書いていて、出力には表層構文で書かれた文字列を渡す必要があるのですが、単純にCoreExprをpprしてしまうと、Haskellの構文ではなくなってしまいます。\nそれなので、CoreをHsに戻すまで行かなくても、パースに通るようなテキストに変換したいです。",
        "type": "message",
        "user": "U02CE9YGEAU"
    },
    {
        "ts": "1715333242.761969",
        "text": "なさそうなら、自前で実装するか",
        "type": "message",
        "user": "U02CE9YGEAU"
    }
]