[
    {
        "ts": "1537054598.000100",
        "text": "反映しました :bow:",
        "user": "U4KPPQW7K",
        "type": "message"
    },
    {
        "ts": "1537236033.000100",
        "text": "なんと :cry:\n<https://twitter.com/rider_yi/status/1041863057364795392>",
        "user": "U4KPPQW7K",
        "type": "message"
    },
    {
        "ts": "1537243269.000100",
        "text": "ちなみに、名古屋芋煮会とも被ってるw\n<https://cookingnagoya.connpass.com/event/100989/>",
        "user": "U56L7EVNY",
        "type": "message"
    },
    {
        "ts": "1537243558.000100",
        "text": "名古屋勢は芋煮会に吸われているので影響が大きそう",
        "user": "U4KUNQF9N",
        "type": "message"
    },
    {
        "ts": "1537268679.000100",
        "text": "それな",
        "user": "U56L7EVNY",
        "type": "message"
    },
    {
        "ts": "1537342650.000100",
        "text": "あとなんかもう一つ被ってるのあった気がする",
        "user": "U5LV76EJH",
        "type": "message"
    },
    {
        "ts": "1537342677.000100",
        "text": "偶然がすぎるぜ:sob: ",
        "user": "U5LV76EJH",
        "type": "message"
    },
    {
        "ts": "1537342715.000100",
        "text": "数ヶ月前に探したときに「個々ほかとかぶってないしちょうどいいや！」と思ったところではあるので、みんな同じことを考えたのかもしれません :disappointed_relieved:",
        "user": "U4LGTMTMK",
        "type": "message"
    },
    {
        "ts": "1537542320.000200",
        "text": "<@UCZRZLXDL> has joined the channel",
        "user": "UCZRZLXDL",
        "type": "message"
    },
    {
        "ts": "1538195733.000200",
        "text": "<@UD33KMXRP> has joined the channel",
        "user": "UD33KMXRP",
        "type": "message"
    },
    {
        "ts": "1538223326.000200",
        "text": "<@U5N5E13NW> has joined the channel",
        "user": "U5N5E13NW",
        "type": "message"
    },
    {
        "ts": "1538386445.000100",
        "text": "やっとこさ技術書典5のやつ入稿できたので、今日からHaskell Dayのやつやってる（報告）:open_mouth: ",
        "user": "U5LV76EJH",
        "type": "message"
    },
    {
        "ts": "1538569118.000100",
        "text": "Haskell Dayのやつ、プロットのプロトタイプレベルまでやりましたっ",
        "user": "U5LV76EJH",
        "type": "message"
    },
    {
        "ts": "1538894556.000100",
        "text": "",
        "user": null,
        "type": "message"
    },
    {
        "ts": "1538901293.000100",
        "text": "私のセッション <https://trello.com/c/mVaJAxzV/25-%E3%80%8C%E4%BD%9C%E3%82%8A%E3%81%AA%E3%81%8C%E3%82%89%E5%AD%A6%E3%81%B6haskell%E5%85%A5%E9%96%80%E3%80%8D%E3%82%92%E4%BD%BF%E3%81%A3%E3%81%9F%E3%83%8F%E3%83%B3%E3%82%BA%E3%82%AA%E3%83%B3>\nのリポジトリーをHaskell-jpをownerにして移しました。 <https://github.com/haskell-jp/makeMistakesToLearnHaskell>\nついでに、開発者向けのドキュメントを追加しております。\nどなたか余力があれば、開発に協力いただけると幸いです。 hask(_ _)eller",
        "user": "U4LGTMTMK",
        "type": "message"
    },
    {
        "ts": "1538901678.000100",
        "text": "協力って Issues みて、それやるよーって感じですか？",
        "user": "U56L7EVNY",
        "type": "message"
    },
    {
        "ts": "1538902773.000100",
        "text": "そうですね。当面はIssueの対応になるかと思います。\n<https://github.com/haskell-jp/makeMistakesToLearnHaskell/blob/master/README.md#%E7%89%B9%E3%81%AB%E7%A7%81-igrep%E4%BB%A5%E5%A4%96%E3%81%AB%E3%82%84%E3%81%A3%E3%81%A6%E3%81%84%E3%81%9F%E3%81%A0%E3%81%8D%E3%81%9F%E3%81%84%E3%81%93%E3%81%A8> で触れている\n&gt; 課題の判定処理の実装。\nについては、私が課題を書くのを追いつかせないとやりにくいと思うので。",
        "user": "U4LGTMTMK",
        "type": "message"
    },
    {
        "ts": "1538903157.000100",
        "text": "あ、書いてあった、すいません :bow: ",
        "user": "U56L7EVNY",
        "type": "message"
    },
    {
        "ts": "1538954507.000100",
        "text": "そうそう、 makeMistakesToLearnHaskell の開発ですが、 <#CD87P78HF|mmlh> でコミットログなどを流しています。",
        "user": "U4LGTMTMK",
        "type": "message"
    },
    {
        "ts": "1538979760.000100",
        "text": "すみません、気が変わったので発表内容はextensibleではなくlisztについてのものに変更します。調子が悪いので遅れそうですがスライドを準備しているところです",
        "user": "U4KUNQF9N",
        "type": "message"
    }
]