[
    {
        "ts": "1781431839.453729",
        "text": "前回の経験を元にWorkerとメインスレッドのやり取りを書き直してみましたが、却って動かなくなってしまいました。なんなんだSharedWorker、マジで全然わからん。",
        "type": "message",
        "user": "U4LGTMTMK"
    },
    {
        "ts": "1781438762.571379",
        "text": "どうやらNeovimの :wa で複数のファイルを一度に保存したとき vite に一つ目のファイルの変更しか伝わってない、かつ、GHC版Wasmをロードするときにどこかでハングしているらしい、という二重の現象のせいで話がややこしくなっていることに気付きました。やれやれ。とりあえず書き直し後の方式で前回と同程度の実装（ワーカーがWasmファイルをロードしたことをメインスレッドに伝える）までできたので、次回からは多分関数型まつりの資料作りに集中します...",
        "type": "message",
        "user": "U4LGTMTMK"
    }
]