[
    {
        "ts": "1530877756.000050",
        "text": "`~` をホームディレクトリに展開してくれるものは分からないですが、ホームディレクトリが参照できればいいのであれば path と path-io パッケージを使って以下のように書けるはずです。\n```\nh &lt;- getHomeDir\nreadFile $ toFilePath $ h &lt;/&gt; $(mkRelFile \".bashrc\")\n```",
        "user": "U4M598NHM",
        "type": "message"
    },
    {
        "ts": "1530882246.000016",
        "text": "そのGabrielさんの、State of the Haskell ecosystem というのもありますね。\n<https://github.com/Gabriel439/post-rfc/blob/master/sotu.md>",
        "user": "U55V441FS",
        "type": "message"
    }
]